{
    "ticker": "ABVEW",
    "name": "Abviva, Inc.",
    "description": "Abviva, Inc. is a biotechnology company focused on the development and commercialization of innovative therapeutic solutions for patients suffering from chronic diseases. Founded in 2011, Abviva seeks to address unmet medical needs through its proprietary drug delivery systems and advanced formulations. The company\u2019s flagship product is a novel treatment for chronic pain management, which utilizes a unique combination of biologics and nanotechnology to enhance efficacy while minimizing side effects. Abviva is committed to rigorous research and development, working closely with leading medical institutions and regulatory bodies to ensure the safety and effectiveness of its products. The company is also exploring potential applications of its technology in the fields of oncology and regenerative medicine. With a strong emphasis on patient-centered care, Abviva aims to improve the quality of life for individuals living with debilitating conditions while contributing to the advancement of medical science. The company\u2019s mission is to harness innovation to create a healthier future for all.",
    "industry": [
        "Biotechnology",
        "Pharmaceuticals"
    ],
    "headquarters": "San Diego, California, USA",
    "founded": "2011",
    "website": "https://www.abviva.com",
    "ceo": "Dr. Emily Harper",
    "social_media": {
        "twitter": "https://twitter.com/AbvivaInc",
        "linkedin": "https://www.linkedin.com/company/abviva"
    },
    "investor_relations": "https://ir.abviva.com",
    "key_executives": [
        {
            "name": "Dr. Emily Harper",
            "position": "CEO"
        },
        {
            "name": "John Smith",
            "position": "CFO"
        }
    ],
    "product_categories": [
        {
            "category": "Therapeutics",
            "products": [
                "Chronic Pain Management",
                "Oncology Solutions"
            ]
        }
    ],
    "seo": {
        "meta_title": "Abviva, Inc. | Innovative Therapeutics for Chronic Diseases",
        "meta_description": "Explore Abviva, Inc., a biotechnology company dedicated to developing innovative therapies for chronic disease management. Learn about our mission and products.",
        "keywords": [
            "Abviva",
            "Biotechnology",
            "Chronic Pain",
            "Therapeutics",
            "Drug Delivery",
            "Nanotechnology"
        ]
    },
    "faq": [
        {
            "question": "What is Abviva known for?",
            "answer": "Abviva is known for its innovative therapeutic solutions for chronic disease management."
        },
        {
            "question": "Who is the CEO of Abviva?",
            "answer": "Dr. Emily Harper is the CEO of Abviva, Inc."
        },
        {
            "question": "Where is Abviva headquartered?",
            "answer": "Abviva is headquartered in San Diego, California, USA."
        },
        {
            "question": "What are Abviva's main products?",
            "answer": "Abviva's main products include solutions for chronic pain management and oncology."
        },
        {
            "question": "When was Abviva founded?",
            "answer": "Abviva was founded in 2011."
        }
    ],
    "competitors": [
        "AMGN",
        "GILD",
        "REGN",
        "VRTX"
    ],
    "related_stocks": [
        "JNJ",
        "PFE",
        "MRK",
        "ABBV"
    ]
}