{
    "ticker": "AJX",
    "name": "Ajax Resources, Inc.",
    "description": "Ajax Resources, Inc. is a dynamic player in the mining and mineral exploration industry, focusing primarily on the extraction of precious metals and minerals. Established in 2010, the company is dedicated to sustainable mining practices while maximizing resource recovery. Ajax operates several projects in North America, leveraging advanced technology and innovative techniques to enhance efficiency and reduce environmental impact. The company's flagship operation, the Ajax Gold Project, is located in a mineral-rich region, providing significant opportunities for gold and silver extraction. Ajax is committed to maintaining high standards of safety and environmental stewardship, continuously engaging with local communities and stakeholders to ensure responsible mining practices. With a strong team of geologists and mining engineers, Ajax Resources aims to expand its portfolio through strategic acquisitions and exploration, while delivering value to its shareholders. The company\u2019s mission is to become a leading name in the mining sector, recognized for its ethical practices and operational excellence.",
    "industry": [
        "Mining",
        "Metals & Minerals"
    ],
    "headquarters": "Toronto, Ontario, Canada",
    "founded": "2010",
    "website": "https://www.ajaxresources.com",
    "ceo": "Michael Johnson",
    "social_media": {
        "twitter": "https://twitter.com/AjaxResources",
        "linkedin": "https://www.linkedin.com/company/ajax-resources/"
    },
    "investor_relations": "https://ir.ajaxresources.com",
    "key_executives": [
        {
            "name": "Michael Johnson",
            "position": "CEO"
        },
        {
            "name": "Sarah Lee",
            "position": "CFO"
        }
    ],
    "product_categories": [
        {
            "category": "Mining Operations",
            "products": [
                "Gold",
                "Silver"
            ]
        },
        {
            "category": "Exploration Projects",
            "products": [
                "Ajax Gold Project"
            ]
        }
    ],
    "seo": {
        "meta_title": "Ajax Resources, Inc. | Sustainable Mining and Mineral Exploration",
        "meta_description": "Explore Ajax Resources, Inc., a leader in sustainable mining and mineral exploration focused on precious metals. Discover our projects and commitment to responsible practices.",
        "keywords": [
            "Ajax Resources",
            "Mining",
            "Gold",
            "Silver",
            "Sustainable Mining",
            "Mineral Exploration"
        ]
    },
    "faq": [
        {
            "question": "What does Ajax Resources focus on?",
            "answer": "Ajax Resources focuses on the mining and exploration of precious metals, primarily gold and silver."
        },
        {
            "question": "Who is the CEO of Ajax Resources?",
            "answer": "Michael Johnson is the CEO of Ajax Resources, Inc."
        },
        {
            "question": "Where is Ajax Resources headquartered?",
            "answer": "Ajax Resources is headquartered in Toronto, Ontario, Canada."
        },
        {
            "question": "What is Ajax's main project?",
            "answer": "Ajax's main project is the Ajax Gold Project, located in a mineral-rich area."
        },
        {
            "question": "When was Ajax Resources founded?",
            "answer": "Ajax Resources was founded in 2010."
        }
    ],
    "competitors": [
        "GOLD",
        "NEM",
        "AUY",
        "KGC"
    ],
    "related_stocks": [
        "AEM",
        "FNV",
        "WPM",
        "SLV"
    ]
}