{
    "ticker": "CE",
    "name": "Celanese Corporation",
    "description": "Celanese Corporation is a global technology and specialty materials company that engineers and produces a wide range of advanced materials and solutions. Founded in 1918 and headquartered in Dallas, Texas, Celanese operates in various sectors, including automotive, medical, electronics, and consumer goods. The company's core products include acetic acid, acetate, and engineered polymers, which are essential components in the manufacture of everyday products. With a commitment to innovation, Celanese focuses on developing sustainable solutions, leveraging its advanced technologies to meet the evolving needs of its customers. Celanese's global reach is complemented by its diverse manufacturing capabilities, enabling the company to serve clients across multiple industries. The company is dedicated to sustainability, aiming to reduce its environmental footprint through efficient production processes and responsible sourcing. Celanese's mission is to create value for its customers, shareholders, and communities by delivering high-quality products and services while fostering a culture of safety and responsibility.",
    "industry": [
        "Chemicals",
        "Materials"
    ],
    "headquarters": "Dallas, Texas, USA",
    "founded": "1918",
    "website": "https://www.celanese.com",
    "ceo": "Lori Ryerkerk",
    "social_media": {
        "twitter": "https://twitter.com/celanese",
        "linkedin": "https://www.linkedin.com/company/celanese/"
    },
    "investor_relations": "https://ir.celanese.com",
    "key_executives": [
        {
            "name": "Lori Ryerkerk",
            "position": "CEO"
        },
        {
            "name": "Chris R. B. G. K. H. Capelle",
            "position": "CFO"
        }
    ],
    "product_categories": [
        {
            "category": "Specialty Materials",
            "products": [
                "Acetic Acid",
                "Acetate",
                "Engineered Polymers"
            ]
        },
        {
            "category": "Industrial Chemicals",
            "products": [
                "Ethanol",
                "Vinyl Acetate Monomer"
            ]
        }
    ],
    "seo": {
        "meta_title": "Celanese Corporation | Advanced Materials and Solutions",
        "meta_description": "Explore Celanese Corporation, a global leader in engineered materials and specialty chemicals. Discover our innovative solutions and commitment to sustainability.",
        "keywords": [
            "Celanese",
            "Specialty Materials",
            "Chemicals",
            "Sustainability",
            "Acetic Acid",
            "Engineered Polymers"
        ]
    },
    "faq": [
        {
            "question": "What does Celanese Corporation do?",
            "answer": "Celanese Corporation is a global technology and specialty materials company that produces advanced materials and solutions for various industries."
        },
        {
            "question": "Who is the CEO of Celanese?",
            "answer": "Lori Ryerkerk is the CEO of Celanese Corporation."
        },
        {
            "question": "Where is Celanese headquartered?",
            "answer": "Celanese is headquartered in Dallas, Texas, USA."
        },
        {
            "question": "What are Celanese's main products?",
            "answer": "Celanese's main products include acetic acid, acetate, and engineered polymers."
        },
        {
            "question": "When was Celanese founded?",
            "answer": "Celanese was founded in 1918."
        }
    ],
    "competitors": [
        "DD",
        "LYB",
        "MPC"
    ],
    "related_stocks": [
        "AAPL",
        "MSFT",
        "AMZN",
        "GOOGL"
    ]
}