{
    "ticker": "EATZ",
    "name": "Eatz, Inc.",
    "description": "Eatz, Inc. is an innovative tech company specializing in the food delivery industry, leveraging advanced technology to enhance the culinary experience for consumers and restaurants alike. Founded in 2018, Eatz aims to revolutionize how people access food by providing a seamless and efficient platform for ordering meals from a diverse array of local restaurants. With its user-friendly mobile app and website, customers can easily browse menus, place orders, and enjoy fast delivery right to their doorstep. Eatz is committed to supporting local businesses and promotes a wide variety of cuisines, ensuring that customers have access to both popular and hidden culinary gems in their area. The company's proprietary logistics technology optimizes delivery routes, reducing wait times and ensuring food arrives fresh and hot. Eatz also emphasizes sustainability by partnering with eco-friendly packaging suppliers and implementing carbon-neutral delivery options. As a forward-thinking company, Eatz continuously invests in enhancing its platform through AI-driven recommendations, user feedback integration, and loyalty programs designed to reward repeat customers. With a mission to connect people with great food while fostering community ties, Eatz is poised for significant growth in the ever-expanding food delivery market.",
    "industry": [
        "Food Delivery",
        "Technology"
    ],
    "headquarters": "San Francisco, California, USA",
    "founded": "2018",
    "website": "https://www.eatz.com",
    "ceo": "Jane Doe",
    "social_media": {
        "twitter": "https://twitter.com/eatzinc",
        "linkedin": "https://www.linkedin.com/company/eatz-inc/",
        "instagram": "https://www.instagram.com/eatzinc/"
    },
    "investor_relations": "https://ir.eatz.com",
    "key_executives": [
        {
            "name": "Jane Doe",
            "position": "CEO"
        },
        {
            "name": "John Smith",
            "position": "CFO"
        }
    ],
    "product_categories": [
        {
            "category": "Food Delivery",
            "products": [
                "Meal Delivery Service",
                "Restaurant Partnerships"
            ]
        },
        {
            "category": "Technology Solutions",
            "products": [
                "Mobile App",
                "Delivery Logistics Platform"
            ]
        }
    ],
    "seo": {
        "meta_title": "Eatz, Inc. | Innovative Food Delivery Solutions",
        "meta_description": "Explore Eatz, Inc., a tech-driven food delivery company transforming the way you enjoy meals from local restaurants. Discover our platform, partnerships, and commitment to sustainability.",
        "keywords": [
            "Eatz",
            "Food Delivery",
            "Meal Delivery",
            "Restaurant Partnerships",
            "Tech Company"
        ]
    },
    "faq": [
        {
            "question": "What is Eatz known for?",
            "answer": "Eatz is known for its innovative food delivery platform that connects customers with local restaurants."
        },
        {
            "question": "Who is the CEO of Eatz?",
            "answer": "Jane Doe is the CEO of Eatz, Inc."
        },
        {
            "question": "Where is Eatz headquartered?",
            "answer": "Eatz is headquartered in San Francisco, California, USA."
        },
        {
            "question": "What services does Eatz offer?",
            "answer": "Eatz offers meal delivery services and technology solutions for restaurants."
        },
        {
            "question": "When was Eatz founded?",
            "answer": "Eatz was founded in 2018."
        }
    ],
    "competitors": [
        "UBER",
        "GRUB",
        "DOORDASH"
    ],
    "related_stocks": [
        "AMZN",
        "AAPL",
        "GOOGL"
    ]
}