{
    "ticker": "LIPO",
    "name": "Lipo Chemicals Ltd.",
    "description": "Lipo Chemicals Ltd. is a leading manufacturer and supplier of specialty chemicals and personal care ingredients. Founded in 1987, the company has established itself as a trusted partner in the cosmetic, pharmaceutical, and food industries. Lipo Chemicals is known for its innovative solutions that cater to a diverse range of applications, including skin care, hair care, and sun care products. The company focuses on the development of high-performance ingredients that enhance product efficacy, safety, and sensory appeal. With a commitment to sustainability, Lipo Chemicals emphasizes the use of renewable resources and environmentally friendly processes in its manufacturing operations. The company's extensive portfolio includes emollients, emulsifiers, surfactants, and active ingredients, all formulated to meet the growing demands of the global market. Lipo Chemicals prides itself on its customer-centric approach, offering tailored solutions and technical support to clients worldwide. The company operates multiple manufacturing facilities and maintains a robust research and development division, ensuring continuous innovation and compliance with industry standards. Lipo Chemicals is dedicated to fostering long-term relationships with its customers by providing quality products and exceptional service.",
    "industry": [
        "Chemicals",
        "Cosmetics",
        "Pharmaceuticals"
    ],
    "headquarters": "Mumbai, India",
    "founded": "1987",
    "website": "https://www.lipochemicals.com",
    "ceo": "Rajesh Mehta",
    "social_media": {
        "twitter": "https://twitter.com/lipochemicals",
        "linkedin": "https://www.linkedin.com/company/lipo-chemicals-ltd-"
    },
    "investor_relations": "https://www.lipochemicals.com/investor-relations",
    "key_executives": [
        {
            "name": "Rajesh Mehta",
            "position": "CEO"
        },
        {
            "name": "Anita Desai",
            "position": "CFO"
        }
    ],
    "product_categories": [
        {
            "category": "Personal Care Ingredients",
            "products": [
                "Emollients",
                "Emulsifiers",
                "Surfactants",
                "Active Ingredients"
            ]
        },
        {
            "category": "Pharmaceutical Ingredients",
            "products": [
                "Excipients",
                "Active Pharmaceutical Ingredients"
            ]
        }
    ],
    "seo": {
        "meta_title": "Lipo Chemicals Ltd. | Specialty Chemicals for Personal Care",
        "meta_description": "Explore Lipo Chemicals Ltd., a leader in specialty chemicals and personal care ingredients. Discover innovative solutions for cosmetics and pharmaceuticals.",
        "keywords": [
            "Lipo Chemicals",
            "Specialty Chemicals",
            "Personal Care Ingredients",
            "Cosmetics",
            "Pharmaceuticals",
            "Emollients",
            "Emulsifiers"
        ]
    },
    "faq": [
        {
            "question": "What does Lipo Chemicals specialize in?",
            "answer": "Lipo Chemicals specializes in the manufacturing of specialty chemicals and personal care ingredients."
        },
        {
            "question": "Who is the CEO of Lipo Chemicals?",
            "answer": "Rajesh Mehta is the CEO of Lipo Chemicals Ltd."
        },
        {
            "question": "Where is Lipo Chemicals headquartered?",
            "answer": "Lipo Chemicals is headquartered in Mumbai, India."
        },
        {
            "question": "What are the main product categories of Lipo Chemicals?",
            "answer": "Lipo Chemicals' main product categories include personal care ingredients and pharmaceutical ingredients."
        },
        {
            "question": "When was Lipo Chemicals founded?",
            "answer": "Lipo Chemicals was founded in 1987."
        }
    ],
    "competitors": [
        "AVP",
        "COLG",
        "SHW",
        "UNVR"
    ],
    "related_stocks": [
        "PG",
        "CL",
        "CHD",
        "EL"
    ]
}