{
    "ticker": "MKAM",
    "name": "MKA Management, Inc.",
    "description": "MKA Management, Inc. is a leading consulting and management services company specializing in strategic planning, project management, and operational efficiency for businesses across various sectors. Founded in 2010, MKA has established a reputation for delivering innovative solutions that help organizations navigate complex challenges in an ever-evolving market landscape. The company focuses on empowering its clients through tailored strategies that enhance productivity, streamline operations, and drive sustainable growth. With a team of experienced professionals, MKA Management offers a comprehensive suite of services including business analysis, risk management, organizational development, and change management. MKA's commitment to excellence and client satisfaction has led to long-lasting partnerships with both private and public sector organizations. The firm prides itself on its ability to adapt to the unique needs of each client, leveraging data-driven insights and industry best practices to achieve measurable results. MKA Management is dedicated to fostering a culture of innovation and continuous improvement, ensuring that clients not only meet their strategic goals but also position themselves for future success in their respective industries.",
    "industry": [
        "Consulting",
        "Management Services"
    ],
    "headquarters": "New York, New York, USA",
    "founded": "2010",
    "website": "https://www.mkamanagement.com",
    "ceo": "Michael K. Anderson",
    "social_media": {
        "twitter": "https://twitter.com/mkamanagement",
        "linkedin": "https://www.linkedin.com/company/mka-management"
    },
    "investor_relations": "https://www.mkamanagement.com/investor-relations",
    "key_executives": [
        {
            "name": "Michael K. Anderson",
            "position": "CEO"
        },
        {
            "name": "Sarah L. Thompson",
            "position": "CFO"
        }
    ],
    "product_categories": [
        {
            "category": "Consulting Services",
            "products": [
                "Strategic Planning",
                "Project Management",
                "Operational Efficiency"
            ]
        }
    ],
    "seo": {
        "meta_title": "MKA Management, Inc. | Leading Consulting and Management Services",
        "meta_description": "Explore MKA Management, Inc., a top consulting firm dedicated to providing innovative solutions and managing operational efficiency for businesses. Learn about our services and commitment to client success.",
        "keywords": [
            "MKA Management",
            "Consulting",
            "Management Services",
            "Strategic Planning",
            "Project Management"
        ]
    },
    "faq": [
        {
            "question": "What services does MKA Management provide?",
            "answer": "MKA Management offers consulting services including strategic planning, project management, and operational efficiency."
        },
        {
            "question": "Who is the CEO of MKA Management?",
            "answer": "Michael K. Anderson is the CEO of MKA Management, Inc."
        },
        {
            "question": "Where is MKA Management headquartered?",
            "answer": "MKA Management is headquartered in New York, New York, USA."
        },
        {
            "question": "When was MKA Management founded?",
            "answer": "MKA Management was founded in 2010."
        }
    ],
    "competitors": [
        "Bain",
        "McKinsey",
        "BCG"
    ],
    "related_stocks": [
        "IBM",
        "ADBE",
        "ORCL"
    ]
}