{
    "ticker": "NEXI",
    "name": "Nexi S.p.A.",
    "description": "Nexi S.p.A. is a leading Italian payment services provider, specializing in digital payments and financial technology. Founded in 2017, Nexi has rapidly established itself as a crucial player in the evolving landscape of cashless transactions in Italy and Europe. The company provides a comprehensive suite of payment solutions for consumers, merchants, and banks, including point-of-sale (POS) systems, e-commerce payment gateways, and mobile payment solutions. Nexi aims to simplify the payment process for businesses and enhance the customer experience by offering innovative tools and services that meet the demands of a digital economy. With a focus on security and reliability, Nexi utilizes advanced technologies to ensure safe transactions and protect customer data. The company is committed to driving the digital transformation of payments, contributing to a cashless society through partnerships with various stakeholders in the financial ecosystem. Nexi's ambition is underscored by its continuous investment in technology and customer-centric solutions, making it a preferred choice for businesses looking to optimize their payment processes.",
    "industry": [
        "Financial Technology",
        "Payment Processing"
    ],
    "headquarters": "Milan, Italy",
    "founded": "2017",
    "website": "https://www.nexi.it",
    "ceo": "Paolo Bertoluzzo",
    "social_media": {
        "twitter": "https://twitter.com/nexiitalia",
        "linkedin": "https://www.linkedin.com/company/nexi/"
    },
    "investor_relations": "https://www.nexi.it/investor-relations",
    "key_executives": [
        {
            "name": "Paolo Bertoluzzo",
            "position": "CEO"
        },
        {
            "name": "Cristina De Lazzari",
            "position": "CFO"
        }
    ],
    "product_categories": [
        {
            "category": "Payment Solutions",
            "products": [
                "POS Systems",
                "E-commerce Payment Gateways",
                "Mobile Payment Solutions"
            ]
        },
        {
            "category": "Financial Services",
            "products": [
                "Merchant Services",
                "Fraud Prevention Tools"
            ]
        }
    ],
    "seo": {
        "meta_title": "Nexi S.p.A. | Leading Digital Payment Solutions in Italy",
        "meta_description": "Explore Nexi S.p.A., a premier provider of digital payment solutions in Italy. Discover our innovative services for businesses and consumers.",
        "keywords": [
            "Nexi",
            "Digital Payments",
            "Payment Solutions",
            "Fintech",
            "Cashless Transactions"
        ]
    },
    "faq": [
        {
            "question": "What services does Nexi offer?",
            "answer": "Nexi offers a variety of payment solutions, including POS systems, e-commerce payment gateways, and mobile payment services."
        },
        {
            "question": "Who is the CEO of Nexi?",
            "answer": "Paolo Bertoluzzo is the CEO of Nexi S.p.A."
        },
        {
            "question": "Where is Nexi headquartered?",
            "answer": "Nexi is headquartered in Milan, Italy."
        },
        {
            "question": "When was Nexi founded?",
            "answer": "Nexi was founded in 2017."
        }
    ],
    "competitors": [
        "SQUARE",
        "PAYX",
        "ADYEY"
    ],
    "related_stocks": [
        "AAPL",
        "GOOGL",
        "AMZN",
        "MSFT"
    ]
}