{
    "ticker": "SLRC",
    "name": "Sierra Income Corporation",
    "description": "Sierra Income Corporation is a business development company (BDC) focused on investing in private middle-market companies in the United States. Founded in 2014, the company seeks to provide a diversified portfolio of debt and equity investments in growth-oriented companies. Sierra Income Corporation aims to generate attractive risk-adjusted returns for its shareholders through a combination of income and capital appreciation. The company primarily invests in senior secured loans, subordinated debt, and equity securities, utilizing a disciplined investment approach to identify opportunities with strong management teams and growth potential. Sierra Income Corporation has a strong emphasis on sustainable investing and is committed to supporting companies that prioritize environmental, social, and governance (ESG) practices. With its experienced management team and strategic investment strategy, Sierra Income Corporation is well-positioned to navigate the complexities of the private equity landscape and deliver value to its investors. The company is publicly traded and adheres to the regulatory requirements set forth by the SEC, ensuring transparency and accountability to its shareholders.",
    "industry": [
        "Finance",
        "Investment Management"
    ],
    "headquarters": "New York, New York, USA",
    "founded": "2014",
    "website": "https://www.sierraincomecorp.com",
    "ceo": "Michael J. Dorr",
    "social_media": {
        "linkedin": "https://www.linkedin.com/company/sierra-income-corporation/"
    },
    "investor_relations": "https://www.sierraincomecorp.com/investors",
    "key_executives": [
        {
            "name": "Michael J. Dorr",
            "position": "CEO"
        },
        {
            "name": "David E. Hurst",
            "position": "CFO"
        }
    ],
    "product_categories": [
        {
            "category": "Investment Products",
            "products": [
                "Senior Secured Loans",
                "Subordinated Debt",
                "Equity Securities"
            ]
        }
    ],
    "seo": {
        "meta_title": "Sierra Income Corporation | Business Development Company",
        "meta_description": "Explore Sierra Income Corporation, a leading business development company investing in private middle-market companies. Learn about our investment approach and commitment to sustainable practices.",
        "keywords": [
            "Sierra Income Corporation",
            "BDC",
            "Private Equity",
            "Investment Management",
            "Middle-Market Companies"
        ]
    },
    "faq": [
        {
            "question": "What is Sierra Income Corporation?",
            "answer": "Sierra Income Corporation is a business development company focused on investing in private middle-market companies."
        },
        {
            "question": "Who is the CEO of Sierra Income Corporation?",
            "answer": "Michael J. Dorr is the CEO of Sierra Income Corporation."
        },
        {
            "question": "Where is Sierra Income Corporation headquartered?",
            "answer": "Sierra Income Corporation is headquartered in New York, New York, USA."
        },
        {
            "question": "What types of investments does Sierra Income Corporation make?",
            "answer": "Sierra Income Corporation invests in senior secured loans, subordinated debt, and equity securities."
        },
        {
            "question": "When was Sierra Income Corporation founded?",
            "answer": "Sierra Income Corporation was founded in 2014."
        }
    ],
    "competitors": [
        "TPVG",
        "GBDC",
        "MAIN",
        "ARCC"
    ],
    "related_stocks": [
        "AAPL",
        "MSFT",
        "AMZN",
        "GOOGL"
    ]
}